odoo9_addon_cms_status_message-9.0.1.0.0-py2.7-nspkg.pth
odoo_addons/cms_status_message/__openerp__.py
odoo_addons/cms_status_message/__init__.py
odoo_addons/cms_status_message/README.rst
odoo_addons/cms_status_message/models/__init__.py
odoo_addons/cms_status_message/models/website.py
odoo_addons/cms_status_message/templates/status_message.xml
odoo_addons/cms_status_message/i18n/it.po
odoo_addons/cms_status_message/tests/__init__.py
odoo_addons/cms_status_message/tests/test_message.py
odoo_addons/cms_status_message/images/preview.png
odoo_addons/cms_status_message/static/description/icon.png
odoo9_addon_cms_status_message-9.0.1.0.0.dist-info/top_level.txt
odoo9_addon_cms_status_message-9.0.1.0.0.dist-info/WHEEL
odoo9_addon_cms_status_message-9.0.1.0.0.dist-info/RECORD
odoo9_addon_cms_status_message-9.0.1.0.0.dist-info/metadata.json
odoo9_addon_cms_status_message-9.0.1.0.0.dist-info/DESCRIPTION.rst
odoo9_addon_cms_status_message-9.0.1.0.0.dist-info/METADATA
odoo9_addon_cms_status_message-9.0.1.0.0.dist-info/namespace_packages.txt
